datamorphers/__init__.py
datamorphers/base.py
datamorphers/datamorphers.py
datamorphers/pipeline_loader.py
datamorphers/storage.py
datamorphers/constants/__init__.py
datamorphers/constants/constants.py
datamorphers-1.0.8.dist-info/licenses/LICENSE.txt
tests/test_pipeline.py
tests/test_pydantic_validation.py
tests/test_single_datamorphers.py
tests/test_storage.py
tests/test_validate_pipeline.py
datamorphers-1.0.8.dist-info/METADATA
datamorphers-1.0.8.dist-info/WHEEL
datamorphers-1.0.8.dist-info/top_level.txt
datamorphers-1.0.8.dist-info/RECORD
