Metadata-Version: 2.4
Name: datamorphers
Version: 1.0.8
Summary: Flexible framework for transforming Pandas and Polars DataFrames using a modular data pipeline approach.
Author-email: Davide Ganna <ganna.davide@hotmail.it>
License: MIT
License-File: LICENSE.txt
Requires-Dist: black==22.10.0
Requires-Dist: lxml==5.3.1
Requires-Dist: narwhals==1.32.0
Requires-Dist: pandas==2.2.3
Requires-Dist: pyarrow==19.0.1
Requires-Dist: pydantic==2.11.2
Requires-Dist: PyYAML==6.0.2
Requires-Dist: pytest==8.3.4
Requires-Dist: ruff==0.11.2
Dynamic: license-file
